digisondeindices/__init__.py
digisondeindices/base.py
digisondeindices/io.py
digisondeindices/utils.py
digisondeindices/web.py
digisondeindices-2.0.2.dist-info/METADATA
digisondeindices-2.0.2.dist-info/WHEEL
digisondeindices-2.0.2.dist-info/top_level.txt
digisondeindices-2.0.2.dist-info/RECORD
